MANIFEST.in
Products.SimpleAlias-configure.zcml
setup.cfg
setup.py
Products/.DS_Store
Products/__init__.py
Products/svn-commit.tmp~
Products.SimpleAlias.egg-info/PKG-INFO
Products.SimpleAlias.egg-info/SOURCES.txt
Products.SimpleAlias.egg-info/dependency_links.txt
Products.SimpleAlias.egg-info/entry_points.txt
Products.SimpleAlias.egg-info/namespace_packages.txt
Products.SimpleAlias.egg-info/not-zip-safe
Products.SimpleAlias.egg-info/requires.txt
Products.SimpleAlias.egg-info/top_level.txt
Products/SimpleAlias/CHANGES
Products/SimpleAlias/CREDITS.txt
Products/SimpleAlias/LICENSE.txt
Products/SimpleAlias/Permissions.py
Products/SimpleAlias/README.txt
Products/SimpleAlias/SimpleAliasTool.py
Products/SimpleAlias/__init__.py
Products/SimpleAlias/config.py
Products/SimpleAlias/configure.zcml
Products/SimpleAlias/subscribers.py
Products/SimpleAlias/tool.gif
Products/SimpleAlias/version.txt
Products/SimpleAlias/content/__init__.py
Products/SimpleAlias/content/alias.py
Products/SimpleAlias/exportimport/__init__.py
Products/SimpleAlias/exportimport/configure.zcml
Products/SimpleAlias/exportimport/properties.py
Products/SimpleAlias/i18n/simplealias-fr.po
Products/SimpleAlias/i18n/simplealias-nl.po
Products/SimpleAlias/i18n/simplealias-plone-fr.po
Products/SimpleAlias/i18n/simplealias-plone-nl.po
Products/SimpleAlias/i18n/simplealias-plone.pot
Products/SimpleAlias/i18n/simplealias.pot
Products/SimpleAlias/interfaces/__init__.py
Products/SimpleAlias/interfaces/alias.py
Products/SimpleAlias/profiles/default/actions.xml
Products/SimpleAlias/profiles/default/factorytool.xml
Products/SimpleAlias/profiles/default/metadata.xml
Products/SimpleAlias/profiles/default/rolemap.xml
Products/SimpleAlias/profiles/default/simplealias.xml
Products/SimpleAlias/profiles/default/skins.xml
Products/SimpleAlias/profiles/default/toolset.xml
Products/SimpleAlias/profiles/default/types.xml
Products/SimpleAlias/profiles/default/workflows.xml
Products/SimpleAlias/profiles/default/types/Alias.xml
Products/SimpleAlias/skins/SimpleAlias/alias-arrow.gif
Products/SimpleAlias/skins/SimpleAlias/alias-arrow.gif.metadata
Products/SimpleAlias/skins/SimpleAlias/alias_icon.gif
Products/SimpleAlias/skins/SimpleAlias/alias_icon.gif.metadata
Products/SimpleAlias/skins/SimpleAlias/alias_view.pt
Products/SimpleAlias/skins/SimpleAlias/document_icon_alias.gif
