Metadata-Version: 1.0
Name: Products.SimpleAlias
Version: 2.1.1
Summary: SimpleAlias is a product that let's you create aliases or shortcuts to content somewhere in your Plone.
Home-page: http://plone.org/products/simplealias
Author: Danny Bloemendaal
Author-email: danny.bloemendaal@informaat.nl
License: GPL
Keywords: web zope plone alias
Platform: UNKNOWN
Classifier: Framework :: Plone
Classifier: Programming Language :: Python
Classifier: Topic :: Software Development :: Libraries :: Python Modules
